freshman/DCD/lab/lab 3/Lab3_SbRb_Latch_gatelevel.v
module Lab3_SbRb_Latch_gatelevel(input Sb, Rb, output Q, Qb);
    nand#(5) (Qb,Q,Rb);
    nand#(5) (Q,Qb,Sb);
endmodule

freshman/DCD/lab/lab 3/t_Lab3_SbRb_Latch_gatelevel.v
module t_Lab3_SbRb_Latch_gatelevel();
    wire    Q,Qb;
    reg     Sb,Rb;

    Lab3_SbRb_Latch_gatelevel M1(Sb,Rb,Q,Qb);

    initial begin
            Sb = 1'b0;  Rb = 1'b1;
            #30 Sb = 1'b1;
            #30 Rb = 1'b0;
            #30 Rb = 1'b1;
            #30 Sb = 1'b0;  Rb = 1'b0;
            #30 Sb = 1'b1;  Rb = 1'b1;
            #30 Sb = 1'b0;
    end
    initial #210 $finish;

    initial begin
            $dumpfile("t_Lab3_SbRb_Latch_gatelevel");
            $dumpvars;
    end
endmodule

freshman/DCD/lab/lab 3/t_Lab3_SbRb_Latch_gatelevel.vcd
$date
	Wed Jun 02 13:52:17 2021
$end
$version
	Icarus Verilog
$end
$timescale
	1s
$end
$scope module t_Lab3_SbRb_Latch_gatelevel $end
$var wire 1 ! Qb $end
$var wire 1 " Q $end
$var reg 1 # Rb $end
$var reg 1 $ Sb $end
$scope module M1 $end
$var wire 1 " Q $end
$var wire 1 ! Qb $end
$var wire 1 # Rb $end
$var wire 1 $ Sb $end
$upscope $end
$upscope $end
$enddefinitions $end
#0
$dumpvars
0$
1#
x"
x!
$end
#5
1"
#10
0!
#30
1$
#60
0#
#65
1!
#70
0"
#90
1#
#120
0#
0$
#125
1"
#150
1#
1$
#155
0!
0"
#160
1"
1!
#165
0!
0"
#170
1"
1!
#175
0!
0"
#180
1"
1!
0$
#185
0!
