freshman/DCD/lab/lab 3/D_ff_AR.v
module D_ff_AR(output reg Q, input D, clock, reset);
    always@ (posedge clock, negedge reset)
        if(reset == 0) Q <= 1'b0;
        else Q <= D;
endmodule

freshman/DCD/lab/lab 3/Lab3_Sequence_Recognizer_structure.v
module Lab3_Sequence_Recognizer_structure (input x, clock, reset, output z);
    wire A,B,C,DA,DB,DC;
    assign DA = (x&~C) | (~x&B&C);
    assign DB = (x&C) | (~x&A&~C) | (~x&B&~C);
    assign DC = ~x;
    assign z = (~x&B&~C) | (x&A&C);
    D_ff_AR _A(A,DA,clock,reset);
    D_ff_AR _B(B,DB,clock,reset);
    D_ff_AR _C(C,DC,clock,reset);
endmodule

freshman/DCD/lab/lab 3/Lab3_Sequence_Recognizer_state_diagram.v
module Lab3_Sequence_Recognizer_state_diagram (input x, clock, reset, output reg z);
    reg[2:0] state,next_state;
    initial state = 3'b000;
    parameter S0 = 3'b000, S1 = 3'b001, S2 = 3'b010, S3 = 3'b011, S4 = 3'b100, S5 = 3'b101;
    always@(posedge clock,negedge reset)
        if(reset == 0) state <= S0;
        else state <= next_state;

    always@(state,x)
        case(state)
            S0:if(x) next_state = S4; else next_state = S1;
            S1:if(x) next_state = S2; else next_state = S1;
            S2:if(x) next_state = S4; else next_state = S3;
            S3:if(x) next_state = S2; else next_state = S5;
            S4:if(x) next_state = S4; else next_state = S3;
            S5:if(x) next_state = S2; else next_state = S1;
        endcase

    always@(state,x)
        case(state)
            S2:if(~x) z = 1; else z = 0;
            S5:if(x) z = 1; else z = 0;
            S0,S1,S3,S4: z = 0;
        endcase
endmodule

freshman/DCD/lab/lab 3/t_Lab3_Sequence_Recognizer.v
module t_Lab3_Sequence_Recognizer();
    wire z1,z2;
    reg clock,reset,x;

    Lab3_Sequence_Recognizer_state_diagram state_diagram(x,clock,reset,z1);
    Lab3_Sequence_Recognizer_structure structure(x,clock,reset,z2);
    initial #160 $finish;

    initial begin
        clock = 1;
        reset = 0;
        #3 reset = 1;
        forever
            #5 clock = ~clock;
    end

    initial begin
        #10 x = 0;
        #10 x = 0;
        #10 x = 1;
        #10 x = 1;
        #10 x = 1;
        #10 x = 0;
        #10 x = 0;
        #10 x = 0;
        #10 x = 1;
        #10 x = 0;
        #10 x = 0;
        #10 x = 1;
        #10 x = 0;
        #10 x = 1;
    end
    initial begin
            $dumpfile("t_Lab3_Sequence_Recognizer");
            $dumpvars;
    end
endmodule

freshman/DCD/lab/lab 3/t_Lab3_Sequence_Recognizer.vcd
$date
	Mon May 31 23:17:41 2021
$end
$version
	Icarus Verilog
$end
$timescale
	1s
$end
$scope module t_Lab3_Sequence_Recognizer $end
$var wire 1 ! z2 $end
$var wire 1 " z1 $end
$var reg 1 # clock $end
$var reg 1 $ reset $end
$var reg 1 % x $end
$scope module state_diagram $end
$var wire 1 # clock $end
$var wire 1 $ reset $end
$var wire 1 % x $end
$var reg 3 & next_state [2:0] $end
$var reg 3 ' state [2:0] $end
$var reg 1 " z $end
$upscope $end
$scope module structure $end
$var wire 1 ( DA $end
$var wire 1 ) DB $end
$var wire 1 * DC $end
$var wire 1 # clock $end
$var wire 1 $ reset $end
$var wire 1 % x $end
$var wire 1 ! z $end
$var wire 1 + C $end
$var wire 1 , B $end
$var wire 1 - A $end
$scope module _A $end
$var wire 1 ( D $end
$var wire 1 # clock $end
$var wire 1 $ reset $end
$var reg 1 - Q $end
$upscope $end
$scope module _B $end
$var wire 1 ) D $end
$var wire 1 # clock $end
$var wire 1 $ reset $end
$var reg 1 , Q $end
$upscope $end
$scope module _C $end
$var wire 1 * D $end
$var wire 1 # clock $end
$var wire 1 $ reset $end
$var reg 1 + Q $end
$upscope $end
$upscope $end
$upscope $end
$enddefinitions $end
#0
$dumpvars
0-
0,
0+
x*
0)
x(
b0 '
b1 &
x%
0$
1#
0"
0!
$end
#3
1$
#8
0#
#10
0(
1*
0%
#13
1+
b1 '
1#
#18
0#
#23
1#
#28
0#
#30
1)
b10 &
0*
1%
#33
0)
1(
b100 &
0+
1,
b10 '
1#
#38
0#
#43
b100 '
1-
0,
1#
#48
0#
#53
1#
#58
0#
#60
1)
0(
b11 &
1*
0%
#63
0)
1(
b101 &
b11 '
0-
1,
1+
1#
#68
0#
#73
0(
b1 &
0,
1-
b101 '
1#
#78
0#
#83
b1 '
0-
1#
#88
0#
#90
1)
b10 &
0*
1%
#93
0)
1(
b100 &
0+
1,
b10 '
1#
#98
0#
#100
1)
1!
0(
1"
b11 &
1*
0%
#103
0!
0)
1(
b101 &
0"
b11 '
1+
1#
#108
0#
#113
0(
b1 &
0,
1-
b101 '
1#
#118
0#
#120
1)
1!
b10 &
1"
0*
1%
#123
0)
1(
0!
0"
b100 &
b10 '
0-
1,
0+
1#
#128
0#
#130
1)
1!
0(
b11 &
1"
1*
0%
#133
0!
0)
1(
0"
b101 &
1+
b11 '
1#
#138
0#
#140
0(
1)
b10 &
0*
1%
#143
0)
1(
b100 &
b10 '
0+
1#
#148
0#
#153
0,
1-
b100 '
1#
