freshman/DCD/lab/lab 2/Lab2_encoder_5bit_behavior.v
module Lab2_encoder_5bit_behavior(input [0:4] D, output [2:0] A, output V);
	reg A,V;
	always@(D)
	begin
		V = 1;
		if(D[0]==1) A=3'b000;
		else if(D[1]==1) A=3'b001;
		else if(D[2]==1) A=3'b010;
		else if(D[3]==1) A=3'b011;
		else if(D[4]==1) A=3'b100;
		else		 V=1'b0;
	end
endmodule

freshman/DCD/lab/lab 2/Lab2_encoder_5bit_dataflow.v
module Lab2_encoder_5bit_dataflow(input [0:4] D, output [2:0] A, output V);
	assign	V = D[0]|D[1]|D[2]|D[3]|D[4];
	assign	A[0] = !D[0]&(D[1]|(!D[2]&D[3]));
	assign	A[1] = !D[0]&!D[1]&(D[2]|D[3]);
	assign	A[2] = !D[0]&!D[1]&!D[2]&!D[3]&D[4];
endmodule

freshman/DCD/lab/lab 2/Lab2_encoder_5bit_gate_level.v
module Lab2_encoder_5bit_gate_level (input [0:4] D, output [2:0] A, output V);
	wire	w1,w2,w3;
	or	(V,D[0],D[1],D[2],D[3],D[4]);
	not	(w1,D[0]);
	and	(w2,w1,D[1]);
	not	(w3,D[1]);
	not	(w4,D[2]);
	and	(w5,w3,w4,D[3]);
	or	(A[0],w2,w5);
	or	(w6,D[2],D[3]);
	and	(A[1],w1,w3,w6);
	not	(w7,D[3]);
	and	(A[2],w1,w3,w4,w7,D[4]);
endmodule

freshman/DCD/lab/lab 2/t_Lab2_encoder_5bit.v
module t_Lab2_encoder_5bit();
	wire	[2:0] A1;
	wire	[2:0] A2;
	wire	[2:0] A3;
	wire	V1,V2,V3;
	reg	[0:4] D;

	Lab2_encoder_5bit_gate_level M0(D,A1,V1);
	Lab2_encoder_5bit_dataflow M1(D,A2,V2);
	Lab2_encoder_5bit_behavior M2(D,A3,V3);

	initial begin
		D=5'b00000;
		#50 D=5'b00001;
		#50 D=5'b00011;
		#50 D=5'b00110;
		#50 D=5'b01001;
		#50 D=5'b01101;
		#50 D=5'b10110;
		#50 D=5'b11010;
	end
	initial	#400 $finish;

	initial begin
		$dumpfile("t_Lab2_encoder_5bit.vcd");
		$dumpvars;
	end
endmodule

freshman/DCD/lab/lab 2/t_Lab2_encoder_5bit.vcd
$date
	Mon May 10 20:57:39 2021
$end
$version
	Icarus Verilog
$end
$timescale
	1s
$end
$scope module t_Lab2_encoder_5bit $end
$var wire 1 ! V3 $end
$var wire 1 " V2 $end
$var wire 1 # V1 $end
$var wire 3 $ A3 [2:0] $end
$var wire 3 % A2 [2:0] $end
$var wire 3 & A1 [2:0] $end
$var reg 5 ' D [0:4] $end
$scope module M0 $end
$var wire 5 ( D [0:4] $end
$var wire 1 # V $end
$var wire 1 ) w1 $end
$var wire 1 * w2 $end
$var wire 1 + w3 $end
$var wire 1 , w4 $end
$var wire 1 - w5 $end
$var wire 1 . w6 $end
$var wire 1 / w7 $end
$var wire 3 0 A [2:0] $end
$upscope $end
$scope module M1 $end
$var wire 5 1 D [0:4] $end
$var wire 1 " V $end
$var wire 3 2 A [2:0] $end
$upscope $end
$scope module M2 $end
$var wire 5 3 D [0:4] $end
$var reg 3 4 A [2:0] $end
$var reg 1 ! V $end
$upscope $end
$upscope $end
$enddefinitions $end
#0
$dumpvars
bx 4
b0 3
b0 2
b0 1
b0 0
1/
0.
0-
1,
1+
0*
1)
b0 (
b0 '
b0 &
b0 %
bx $
0#
0"
0!
$end
#50
1#
b100 &
b100 0
1"
b100 %
b100 2
b100 $
b100 4
1!
b1 '
b1 (
b1 1
b1 3
#100
b11 &
b11 0
b11 %
b11 2
1-
1.
0/
b11 $
b11 4
b11 '
b11 (
b11 1
b11 3
#150
b10 &
b10 0
b10 %
b10 2
0-
0,
b10 $
b10 4
b110 '
b110 (
b110 1
b110 3
#200
b1 &
b1 0
b1 %
b1 2
1*
0+
1,
0.
1/
b1 $
b1 4
b1001 '
b1001 (
b1001 1
b1001 3
#250
0,
1.
b1101 '
b1101 (
b1101 1
b1101 3
#300
b0 &
b0 0
0)
0*
1+
0/
b0 %
b0 2
b0 $
b0 4
b10110 '
b10110 (
b10110 1
b10110 3
#350
0+
1,
b11010 '
b11010 (
b11010 1
b11010 3
