freshman/DCD/lab/lab 2/Lab2_half_sub_gatelevel.v
module Lab2_half_sub_gatelevel(input x, y, output B, D);
	wire	w1;

	xor	#(4) G1(D,x,y);
	not	     G2(w1,x);
	and	#(2) G3(B,w1,y);
endmodule

freshman/DCD/lab/lab 2/t_Lab2_half_sub.v
module	t_Lab2_half_sub();
	wire	B,D;
	reg	x,y;

	Lab2_half_sub_gatelevel	M1(x,y,B,D);

	initial begin
		x=1'b0; y=1'b0;
		#50 x=1'b0; y=1'b1;
		#50 x=1'b1; y=1'b0;
		#50 x=1'b1; y=1'b1;
	end
	initial #200 $finish;

	initial begin
		$dumpfile("t_Lab2_half_sub.vcd");
		$dumpvars;
	end
endmodule

freshman/DCD/lab/lab 2/t_Lab2_half_sub.vcd
$date
	Mon May 10 18:08:56 2021
$end
$version
	Icarus Verilog
$end
$timescale
	1s
$end
$scope module t_Lab2_half_sub $end
$var wire 1 ! D $end
$var wire 1 " B $end
$var reg 1 # x $end
$var reg 1 $ y $end
$scope module M1 $end
$var wire 1 " B $end
$var wire 1 ! D $end
$var wire 1 % w1 $end
$var wire 1 # x $end
$var wire 1 $ y $end
$upscope $end
$upscope $end
$enddefinitions $end
#0
$dumpvars
1%
0$
0#
x"
x!
$end
#2
0"
#4
0!
#50
1$
#52
1"
#54
1!
#100
0%
0$
1#
#102
0"
#150
1$
#154
0!
